parsini/__init__.py
parsini/example.py
parsini/parsini.py
parsini-0.0.5.dist-info/LICENSE
parsini-0.0.5.dist-info/METADATA
parsini-0.0.5.dist-info/WHEEL
parsini-0.0.5.dist-info/top_level.txt
parsini-0.0.5.dist-info/RECORD
