Metadata-Version: 2.1
Name: parsini
Version: 0.0.5
Summary: Parsea en formato dict y actualiza fichero de configuración
Home-page: https://github.com/gmolino/parsini
Author: Álvaro García
Author-email: alvaro.garcia.molino@gmail.com
License: UNKNOWN
Platform: UNKNOWN
Classifier: Programming Language :: Python :: 3
Classifier: License :: OSI Approved :: MIT License
Classifier: Operating System :: OS Independent
